Metadata-Version: 1.0
Name: pybcra
Version: 0.1.0
Summary: Estadisticas del Banco Central de la Republica Argentina.
Home-page: https://github.com/maekos/pybcra
Author: maekos
Author-email: maekos@gmail.com
License: UNKNOWN
Platform: UNKNOWN
